{
  "resourceType": "http://hl7.org/fhir/uv/sql-on-fhir/StructureDefinition/ViewDefinition",
  "name": "Location_Telecom",
  "status": "draft",
  "resource": "Location",
  "select": [
    {
      "column": [
        {
          "path": "getResourceKey()",
          "name": "location_id",
          "type": "string"
        }
      ]
    },
    {
      "column": [
        {
          "path": "system",
          "name": "telecom_system",
          "type": "string"
        },
        {
          "path": "value",
          "name": "telecom_value",
          "type": "string"
        }
      ],
      "forEach": "telecom"
    }
  ]
}